{
    "caption": "Folded paper Christmas tree ornament craft for kids. Origami is a great fine motor work activity for kindergarten or elementary children!",
    "url": "https://2.bp.blogspot.com/-ZrN7Fi-WTcU/WDuLMnun0bI/AAAAAAAAL5s/WducGt7ojkElkQIsly5L2WFQruPUN8PuACEw/s640/Origami-Folded-Paper-Christmas-Tree-Ornament-Craft-11.jpg",
    "key": "000270500",
    "status": "success",
    "error_message": null,
    "width": 256,
    "height": 256,
    "original_width": 640,
    "original_height": 449,
    "exif": "{\"Image Software\": \"Google\", \"Image ExifOffset\": \"46\", \"EXIF ExifVersion\": \"\"}",
    "md5": "08f72062e8aa3eb3d8384254900eec40"
}